codestate/__init__.py
codestate/analyzer.py
codestate/cli.py
codestate/visualizer.py
codestate-0.9.4.dist-info/licenses/LICENSE
codestate-0.9.4.dist-info/METADATA
codestate-0.9.4.dist-info/WHEEL
codestate-0.9.4.dist-info/entry_points.txt
codestate-0.9.4.dist-info/top_level.txt
codestate-0.9.4.dist-info/RECORD
