Metadata-Version: 2.4
Name: codestate
Version: 0.9.4
Summary: A CLI tool for codebase statistics and ASCII visualization
Home-page: https://github.com/HenryLok0/CodeState
Author: Henry Lok
Project-URL: Source, https://github.com/HenryLok0/CodeState
Project-URL: Tracker, https://github.com/HenryLok0/CodeState/issues
Project-URL: Documentation, https://github.com/HenryLok0/CodeState#readme
Keywords: code metrics,cli,ascii,static analysis,loc,complexity
Classifier: Programming Language :: Python :: 3
Classifier: License :: OSI Approved :: MIT License
Classifier: Operating System :: OS Independent
Classifier: Topic :: Software Development :: Quality Assurance
Classifier: Topic :: Software Development :: Libraries :: Python Modules
Classifier: Environment :: Console
Classifier: Intended Audience :: Developers
Requires-Python: >=3.7
License-File: LICENSE
Requires-Dist: pathspec
Requires-Dist: openpyxl
Dynamic: author
Dynamic: classifier
Dynamic: description
Dynamic: description-content-type
Dynamic: home-page
Dynamic: keywords
Dynamic: license-file
Dynamic: project-url
Dynamic: requires-dist
Dynamic: requires-python
Dynamic: summary
